apluslms_roman/__init__.py
apluslms_roman/__main__.py
apluslms_roman/builder.py
apluslms_roman/cache_file.py
apluslms_roman/cli.py
apluslms_roman/configuration.py
apluslms_roman/observer.py
apluslms_roman/settings.py
apluslms_roman/backends/__init__.py
apluslms_roman/backends/docker.py
apluslms_roman/schemas/__init__.py
apluslms_roman/schemas/roman_docker_cache-v1.0.json
apluslms_roman/schemas/roman_environment-v1.0.json
apluslms_roman/schemas/roman_project-v2.0.json
apluslms_roman/schemas/roman_settings-v1.0.json
apluslms_roman/schemas/version-v1.0.json
apluslms_roman/utils/__init__.py
apluslms_roman/utils/env.py
apluslms_roman/utils/importing.py
apluslms_roman/utils/translation.py
apluslms_roman-0.3.0rc1.dist-info/LICENSE
apluslms_roman-0.3.0rc1.dist-info/METADATA
apluslms_roman-0.3.0rc1.dist-info/WHEEL
apluslms_roman-0.3.0rc1.dist-info/entry_points.txt
apluslms_roman-0.3.0rc1.dist-info/top_level.txt
apluslms_roman-0.3.0rc1.dist-info/RECORD
