Metadata-Version: 2.1
Name: apluslms-roman
Version: 0.3.0rc1
Summary: Course material builder for online learning systems
Home-page: https://github.com/apluslms/roman
Author: Jaakko Kantojärvi <jaakko.kantojarvi@aalto.fi>
Author-email: apluslms@googlegroups.com
License: MIT
Keywords: apluslms material
Platform: any
Classifier: Development Status :: 4 - Beta
Classifier: License :: OSI Approved :: MIT License
Classifier: Intended Audience :: Developers
Classifier: Operating System :: OS Independent
Classifier: Topic :: Software Development :: Build Tools
Classifier: Topic :: Software Development :: Libraries :: Python Modules
Classifier: Programming Language :: Python :: 3
Classifier: Programming Language :: Python :: 3.5
Classifier: Programming Language :: Python :: 3.6
Classifier: Programming Language :: Python :: 3.7
Classifier: Programming Language :: Python :: 3 :: Only
Requires-Dist: apluslms-yamlidator (==0.3.0rc1)
Requires-Dist: appdirs (<2,>=1.4.0)
Requires-Dist: colorama (~=0.4.1)
Provides-Extra: docker
Requires-Dist: Docker (<4,>=3.0.0) ; extra == 'docker'
